musamusa_romannumbers/aboutproject.py
musamusa_romannumbers/romannumbers.py
musamusa_romannumbers-0.1.3.dist-info/LICENSE
musamusa_romannumbers-0.1.3.dist-info/WHEEL
musamusa_romannumbers-0.1.3.dist-info/METADATA
musamusa_romannumbers-0.1.3.dist-info/RECORD
