Metadata-Version: 2.1
Name: musamusa-romannumbers
Version: 0.1.3
Summary: Roman Numbers (XVI <-> 16)
License: GPLv3
Author: suizokukan
Author-email: suizokukan@orange.fr
Requires-Python: >=3.9,<4.0
Classifier: License :: Other/Proprietary License
Classifier: Programming Language :: Python :: 3
Classifier: Programming Language :: Python :: 3.9
Requires-Dist: musamusa-errors (>=0.9.5,<0.10.0)
